[
  {
    "id": 101,
    "customerName": "Aarav Patel",
    "items": [
      "Margherita Pizza",
      "Garlic Bread"
    ],
    "status": "NEW",
    "createdAt": "2026-03-11T07:10:00.000Z"
  },
  {
    "id": 102,
    "customerName": "Nisha Sharma",
    "items": [
      "Paneer Tikka",
      "Mint Chutney"
    ],
    "status": "NEW",
    "createdAt": "2026-03-11T07:10:30.000Z"
  },
  {
    "id": 103,
    "customerName": "Rohan Mehta",
    "items": [
      "Veg Hakka Noodles",
      "Spring Rolls"
    ],
    "status": "NEW",
    "createdAt": "2026-03-11T07:11:00.000Z"
  },
  {
    "id": 104,
    "customerName": "Priya Iyer",
    "items": [
      "Masala Dosa",
      "Sambar",
      "Coconut Chutney"
    ],
    "status": "PREPARING",
    "createdAt": "2026-03-11T07:05:00.000Z"
  },
  {
    "id": 105,
    "customerName": "Vikram Singh",
    "items": [
      "Chicken Biryani",
      "Raita"
    ],
    "status": "PREPARING",
    "createdAt": "2026-03-11T07:07:00.000Z"
  },
  {
    "id": 106,
    "customerName": "Sana Khan",
    "items": [
      "Caesar Salad",
      "Iced Tea"
    ],
    "status": "PREPARING",
    "createdAt": "2026-03-11T07:08:00.000Z"
  },
  {
    "id": 107,
    "customerName": "Arjun Rao",
    "items": [
      "Cheeseburger",
      "Fries"
    ],
    "status": "READY",
    "createdAt": "2026-03-11T06:55:00.000Z"
  },
  {
    "id": 108,
    "customerName": "Meera Nair",
    "items": [
      "Thai Green Curry",
      "Jasmine Rice"
    ],
    "status": "READY",
    "createdAt": "2026-03-11T06:58:00.000Z"
  },
  {
    "id": 109,
    "customerName": "Kabir Joshi",
    "items": [
      "Penne Arrabbiata",
      "Lemonade"
    ],
    "status": "READY",
    "createdAt": "2026-03-11T07:00:00.000Z"
  },
  {
    "id": 110,
    "customerName": "Ananya Gupta",
    "items": [
      "Falafel Wrap",
      "Hummus"
    ],
    "status": "NEW",
    "createdAt": "2026-03-11T07:12:00.000Z"
  }
]